arxiv_retriever_batch-1.0.2.dist-info/licenses/LICENSE.md
py_arxiv_retriever/__init__.py
py_arxiv_retriever/arxiv_retriever.py
py_arxiv_retriever/axirv_loader.py
arxiv_retriever_batch-1.0.2.dist-info/METADATA
arxiv_retriever_batch-1.0.2.dist-info/WHEEL
arxiv_retriever_batch-1.0.2.dist-info/top_level.txt
arxiv_retriever_batch-1.0.2.dist-info/RECORD
